{
  "bend_radii": [
    [0.02, 0.02, 0.02],
    [0.03, 0.03, 0.03],
    [0.02, 0.02, 0.02],
    [0.03, 0.03, 0.03],
    [0.02, 0.02, 0.02],
    [0.02, 0.02, 0.02],
    [0.02, 0.02, 0.02],
    [0.03, 0.03, 0.03]
  ],
  "twists": [
    [0, 180, 0],
    [0, 180, 0],
    [0, 180, 0],
    [0, 0, 0],
    [0, 0, 0],
    [0, 0, 0],
    [0, 0, 0],
    [0, 0, 0]
  ],
  "inlet_length": [
    0.05, 0.05, 0.05, 0.05, 0.05, 0.05, 0.05, 0.05
  ],
  "outlet_length": [
    0.4, 0.4, 0.4, 0.4, 0.4, 0.4, 0.4, 0.4
  ],
  "connector_lengths": [
    [0.0347, 0.0482],
    [0.0868, 0.0525],
    [0.1842, 0.2564],
    [0.1299, 0.0681],
    [0.2107, 0.0466],
    [0.1254, 0.0625],
    [0.0453, 0.0453],
    [0.1155, 0.1274]
  ],
  "pressure_drop": [
    34106.954,
    35196.35,
    44431.644,
    36652.717,
    39439.792,
    37814.112,
    35597.052,
    37954.29
  ]
}